SymptomSetModel
